inmanta_plugins/exec/__init__.py
inmanta_plugins/exec/py.typed
inmanta_plugins/exec/setup.cfg
inmanta_plugins/exec/model/_init.cf
inmanta_module_exec-2.1.1.dist-info/METADATA
inmanta_module_exec-2.1.1.dist-info/WHEEL
inmanta_module_exec-2.1.1.dist-info/top_level.txt
inmanta_module_exec-2.1.1.dist-info/RECORD
