Metadata-Version: 2.4
Name: inmanta-module-exec
Version: 2.1.1
License: Apache 2.0
Requires-Dist: inmanta-module-std
Requires-Dist: inmanta-module-mitogen
